build_flask_login-0.0.1.data/scripts/build-flask-login
scripts/__init__.py
scripts/manual.py
scripts/messages.py
scripts/workflow.py
build_flask_login-0.0.1.dist-info/LICENSE
build_flask_login-0.0.1.dist-info/METADATA
build_flask_login-0.0.1.dist-info/WHEEL
build_flask_login-0.0.1.dist-info/top_level.txt
build_flask_login-0.0.1.dist-info/RECORD
