Metadata-Version: 2.1
Name: build-flask-login
Version: 0.0.1
Summary: A registration system generator package
Home-page: https://github.com/kouul/build-flask-login
Author: Hans Maulloo
Author-email: maulloohans@gmail.com
License: UNKNOWN
Platform: UNKNOWN
Classifier: Development Status :: 2 - Pre-Alpha
Classifier: Framework :: Flask
Classifier: Intended Audience :: Developers
Classifier: Programming Language :: Python :: 3
Classifier: License :: Freely Distributable
Classifier: Operating System :: OS Independent
Classifier: Topic :: Software Development :: Code Generators
Requires-Dist: colorama
